[
  {
    "ContainingType": "Ecommerce.Controllers.AccountController",
    "Method": "AddAdmin",
    "RelativePath": "api/Account/AddAdmin",
    "HttpMethod": "POST",
    "IsController": true,
    "Order": 0,
    "Parameters": [
      {
        "Name": "email",
        "Type": "System.String",
        "IsRequired": false
      }
    ],
    "ReturnTypes": []
  },
  {
    "ContainingType": "Ecommerce.Controllers.AccountController",
    "Method": "ChangePassword",
    "RelativePath": "api/Account/ChangePassword",
    "HttpMethod": "POST",
    "IsController": true,
    "Order": 0,
    "Parameters": [
      {
        "Name": "changePasswordDTO",
        "Type": "Ecommerce.DTO.ChangePasswordDTO",
        "IsRequired": true
      }
    ],
    "ReturnTypes": []
  },
  {
    "ContainingType": "Ecommerce.Controllers.AccountController",
    "Method": "ConfirmEmail",
    "RelativePath": "api/Account/ConfirmEmail",
    "HttpMethod": "GET",
    "IsController": true,
    "Order": 0,
    "Parameters": [
      {
        "Name": "userId",
        "Type": "System.String",
        "IsRequired": false
      },
      {
        "Name": "token",
        "Type": "System.String",
        "IsRequired": false
      }
    ],
    "ReturnTypes": []
  },
  {
    "ContainingType": "Ecommerce.Controllers.AccountController",
    "Method": "ForgetPassword",
    "RelativePath": "api/Account/ForgetPassword",
    "HttpMethod": "POST",
    "IsController": true,
    "Order": 0,
    "Parameters": [
      {
        "Name": "email",
        "Type": "System.String",
        "IsRequired": false
      }
    ],
    "ReturnTypes": []
  },
  {
    "ContainingType": "Ecommerce.Controllers.AccountController",
    "Method": "Login",
    "RelativePath": "api/Account/Login",
    "HttpMethod": "POST",
    "IsController": true,
    "Order": 0,
    "Parameters": [
      {
        "Name": "logindto",
        "Type": "Ecommerce.DTO.LoginDTO",
        "IsRequired": true
      }
    ],
    "ReturnTypes": []
  },
  {
    "ContainingType": "Ecommerce.Controllers.AccountController",
    "Method": "Register",
    "RelativePath": "api/Account/register",
    "HttpMethod": "POST",
    "IsController": true,
    "Order": 0,
    "Parameters": [
      {
        "Name": "registerdto",
        "Type": "Ecommerce.DTO.RegisterDTO",
        "IsRequired": true
      }
    ],
    "ReturnTypes": []
  },
  {
    "ContainingType": "Ecommerce.Controllers.AccountController",
    "Method": "ResetPassword",
    "RelativePath": "api/Account/ResetPassword",
    "HttpMethod": "GET",
    "IsController": true,
    "Order": 0,
    "Parameters": [
      {
        "Name": "userId",
        "Type": "System.String",
        "IsRequired": false
      },
      {
        "Name": "token",
        "Type": "System.String",
        "IsRequired": false
      },
      {
        "Name": "password",
        "Type": "System.String",
        "IsRequired": false
      }
    ],
    "ReturnTypes": []
  },
  {
    "ContainingType": "Ecommerce.Controllers.CartController",
    "Method": "DeleteFromCart",
    "RelativePath": "api/Cart/{productId}",
    "HttpMethod": "DELETE",
    "IsController": true,
    "Order": 0,
    "Parameters": [
      {
        "Name": "productId",
        "Type": "System.Int32",
        "IsRequired": true
      }
    ],
    "ReturnTypes": []
  },
  {
    "ContainingType": "Ecommerce.Controllers.CartController",
    "Method": "AddProduct",
    "RelativePath": "api/Cart/AddProduct",
    "HttpMethod": "POST",
    "IsController": true,
    "Order": 0,
    "Parameters": [
      {
        "Name": "id",
        "Type": "System.Int32",
        "IsRequired": false
      },
      {
        "Name": "quantity",
        "Type": "System.Int32",
        "IsRequired": false
      }
    ],
    "ReturnTypes": []
  },
  {
    "ContainingType": "Ecommerce.Controllers.CartController",
    "Method": "GetCart",
    "RelativePath": "api/Cart/GetCar",
    "HttpMethod": "GET",
    "IsController": true,
    "Order": 0,
    "Parameters": [],
    "ReturnTypes": []
  },
  {
    "ContainingType": "Ecommerce.Controllers.CategoryController",
    "Method": "GetAll",
    "RelativePath": "api/Category",
    "HttpMethod": "GET",
    "IsController": true,
    "Order": 0,
    "Parameters": [],
    "ReturnTypes": []
  },
  {
    "ContainingType": "Ecommerce.Controllers.CategoryController",
    "Method": "GetById",
    "RelativePath": "api/Category/{id}",
    "HttpMethod": "GET",
    "IsController": true,
    "Order": 0,
    "Parameters": [
      {
        "Name": "id",
        "Type": "System.Int32",
        "IsRequired": true
      }
    ],
    "ReturnTypes": []
  },
  {
    "ContainingType": "Ecommerce.Controllers.CategoryController",
    "Method": "Delete",
    "RelativePath": "api/Category/{id}",
    "HttpMethod": "DELETE",
    "IsController": true,
    "Order": 0,
    "Parameters": [
      {
        "Name": "id",
        "Type": "System.Int32",
        "IsRequired": true
      }
    ],
    "ReturnTypes": []
  },
  {
    "ContainingType": "Ecommerce.Controllers.CategoryController",
    "Method": "GetByName",
    "RelativePath": "api/Category/{name}",
    "HttpMethod": "GET",
    "IsController": true,
    "Order": 0,
    "Parameters": [
      {
        "Name": "name",
        "Type": "System.String",
        "IsRequired": true
      }
    ],
    "ReturnTypes": []
  },
  {
    "ContainingType": "Ecommerce.Controllers.CategoryController",
    "Method": "Add",
    "RelativePath": "api/Category/Add",
    "HttpMethod": "POST",
    "IsController": true,
    "Order": 0,
    "Parameters": [
      {
        "Name": "categoryDTO",
        "Type": "Ecommerce.DTO.CategoryDTO",
        "IsRequired": true
      }
    ],
    "ReturnTypes": []
  },
  {
    "ContainingType": "Ecommerce.Controllers.CategoryController",
    "Method": "Update",
    "RelativePath": "api/Category/Update",
    "HttpMethod": "PUT",
    "IsController": true,
    "Order": 0,
    "Parameters": [
      {
        "Name": "categoryDTO",
        "Type": "Ecommerce.DTO.CategoryDTO",
        "IsRequired": true
      },
      {
        "Name": "id",
        "Type": "System.Int32",
        "IsRequired": false
      }
    ],
    "ReturnTypes": []
  },
  {
    "ContainingType": "Ecommerce.Controllers.OrderController",
    "Method": "Delete",
    "RelativePath": "api/Order/{id}",
    "HttpMethod": "DELETE",
    "IsController": true,
    "Order": 0,
    "Parameters": [
      {
        "Name": "id",
        "Type": "System.Int32",
        "IsRequired": true
      }
    ],
    "ReturnTypes": []
  },
  {
    "ContainingType": "Ecommerce.Controllers.OrderController",
    "Method": "GetAll",
    "RelativePath": "api/Order/GetAll",
    "HttpMethod": "GET",
    "IsController": true,
    "Order": 0,
    "Parameters": [],
    "ReturnTypes": []
  },
  {
    "ContainingType": "Ecommerce.Controllers.OrderController",
    "Method": "GetUserOrders",
    "RelativePath": "api/Order/GetUserOrders",
    "HttpMethod": "GET",
    "IsController": true,
    "Order": 0,
    "Parameters": [],
    "ReturnTypes": []
  },
  {
    "ContainingType": "Ecommerce.Controllers.ProductController",
    "Method": "GetAll",
    "RelativePath": "api/Product",
    "HttpMethod": "GET",
    "IsController": true,
    "Order": 0,
    "Parameters": [],
    "ReturnTypes": []
  },
  {
    "ContainingType": "Ecommerce.Controllers.ProductController",
    "Method": "Add",
    "RelativePath": "api/Product",
    "HttpMethod": "POST",
    "IsController": true,
    "Order": 0,
    "Parameters": [
      {
        "Name": "productdto",
        "Type": "Ecommerce.DTO.ProductPostDTO",
        "IsRequired": true
      }
    ],
    "ReturnTypes": []
  },
  {
    "ContainingType": "Ecommerce.Controllers.ProductController",
    "Method": "Search",
    "RelativePath": "api/Product/{name}",
    "HttpMethod": "GET",
    "IsController": true,
    "Order": 0,
    "Parameters": [
      {
        "Name": "name",
        "Type": "System.String",
        "IsRequired": true
      }
    ],
    "ReturnTypes": []
  },
  {
    "ContainingType": "Ecommerce.Controllers.ProductController",
    "Method": "GetById",
    "RelativePath": "api/Product/{productId}",
    "HttpMethod": "GET",
    "IsController": true,
    "Order": 0,
    "Parameters": [
      {
        "Name": "productId",
        "Type": "System.Int32",
        "IsRequired": true
      }
    ],
    "ReturnTypes": []
  },
  {
    "ContainingType": "Ecommerce.Controllers.ProductController",
    "Method": "Delete",
    "RelativePath": "api/Product/{productId}",
    "HttpMethod": "DELETE",
    "IsController": true,
    "Order": 0,
    "Parameters": [
      {
        "Name": "productId",
        "Type": "System.Int32",
        "IsRequired": true
      }
    ],
    "ReturnTypes": []
  },
  {
    "ContainingType": "Ecommerce.Controllers.ProductController",
    "Method": "Update",
    "RelativePath": "api/Product/{productiId}",
    "HttpMethod": "PUT",
    "IsController": true,
    "Order": 0,
    "Parameters": [
      {
        "Name": "productiId",
        "Type": "System.Int32",
        "IsRequired": true
      },
      {
        "Name": "productdto",
        "Type": "Ecommerce.DTO.ProductPostDTO",
        "IsRequired": true
      }
    ],
    "ReturnTypes": []
  },
  {
    "ContainingType": "Ecommerce.Controllers.ProductController",
    "Method": "GetListByCategory",
    "RelativePath": "api/Product/categoryproduct/{categoryId}",
    "HttpMethod": "GET",
    "IsController": true,
    "Order": 0,
    "Parameters": [
      {
        "Name": "categoryId",
        "Type": "System.Int32",
        "IsRequired": true
      }
    ],
    "ReturnTypes": []
  },
  {
    "ContainingType": "Ecommerce.Controllers.ProductController",
    "Method": "Filtering",
    "RelativePath": "api/Product/Filtering",
    "HttpMethod": "GET",
    "IsController": true,
    "Order": 0,
    "Parameters": [
      {
        "Name": "CategoryName",
        "Type": "System.String",
        "IsRequired": false
      },
      {
        "Name": "Maxprice",
        "Type": "System.Decimal",
        "IsRequired": false
      },
      {
        "Name": "MinPrice",
        "Type": "System.Decimal",
        "IsRequired": false
      },
      {
        "Name": "KeyWord",
        "Type": "System.String",
        "IsRequired": false
      }
    ],
    "ReturnTypes": []
  },
  {
    "ContainingType": "Ecommerce.Controllers.ReviewController",
    "Method": "ProductReview",
    "RelativePath": "api/Review/{productId}",
    "HttpMethod": "GET",
    "IsController": true,
    "Order": 0,
    "Parameters": [
      {
        "Name": "productId",
        "Type": "System.Int32",
        "IsRequired": true
      }
    ],
    "ReturnTypes": []
  },
  {
    "ContainingType": "Ecommerce.Controllers.ReviewController",
    "Method": "DeleteReview",
    "RelativePath": "api/Review/{productId}",
    "HttpMethod": "DELETE",
    "IsController": true,
    "Order": 0,
    "Parameters": [
      {
        "Name": "productId",
        "Type": "System.Int32",
        "IsRequired": true
      }
    ],
    "ReturnTypes": []
  },
  {
    "ContainingType": "Ecommerce.Controllers.ReviewController",
    "Method": "AddReview",
    "RelativePath": "api/Review/AddReview",
    "HttpMethod": "POST",
    "IsController": true,
    "Order": 0,
    "Parameters": [
      {
        "Name": "reviewdto",
        "Type": "Ecommerce.DTO.ReviewDTO",
        "IsRequired": true
      }
    ],
    "ReturnTypes": []
  },
  {
    "ContainingType": "Ecommerce.Controllers.ReviewController",
    "Method": "UpdateReview",
    "RelativePath": "api/Review/UpdateReview",
    "HttpMethod": "PUT",
    "IsController": true,
    "Order": 0,
    "Parameters": [
      {
        "Name": "dto",
        "Type": "Ecommerce.DTO.ReviewDTO",
        "IsRequired": true
      }
    ],
    "ReturnTypes": []
  },
  {
    "ContainingType": "Ecommerce.Controllers.WishListController",
    "Method": "DeleteItem",
    "RelativePath": "api/WishList/{productId}",
    "HttpMethod": "DELETE",
    "IsController": true,
    "Order": 0,
    "Parameters": [
      {
        "Name": "productId",
        "Type": "System.Int32",
        "IsRequired": true
      }
    ],
    "ReturnTypes": []
  },
  {
    "ContainingType": "Ecommerce.Controllers.WishListController",
    "Method": "AddToWishList",
    "RelativePath": "api/WishList/AddToWishList",
    "HttpMethod": "POST",
    "IsController": true,
    "Order": 0,
    "Parameters": [
      {
        "Name": "ProductId",
        "Type": "System.Int32",
        "IsRequired": false
      }
    ],
    "ReturnTypes": []
  },
  {
    "ContainingType": "Ecommerce.Controllers.WishListController",
    "Method": "UserWishList",
    "RelativePath": "api/WishList/UserWishList",
    "HttpMethod": "GET",
    "IsController": true,
    "Order": 0,
    "Parameters": [],
    "ReturnTypes": []
  }
]